django_secure_auth-1.3.3.2.dist-info/DESCRIPTION.rst
django_secure_auth-1.3.3.2.dist-info/METADATA
django_secure_auth-1.3.3.2.dist-info/RECORD
django_secure_auth-1.3.3.2.dist-info/WHEEL
django_secure_auth-1.3.3.2.dist-info/metadata.json
django_secure_auth-1.3.3.2.dist-info/top_level.txt
secureauth/__init__.py
secureauth/admin.py
secureauth/adminsite.py
secureauth/auth_forms.py
secureauth/backend.py
secureauth/defaults.py
secureauth/filters.py
secureauth/forms.py
secureauth/middleware.py
secureauth/models.py
secureauth/tables.py
secureauth/urls.py
secureauth/locale/ru/LC_MESSAGES/django.mo
secureauth/locale/ru/LC_MESSAGES/django.po
secureauth/migrations/0001_initial.py
secureauth/migrations/0002_auto_20170801_0751.py
secureauth/migrations/__init__.py
secureauth/registration/__init__.py
secureauth/registration/urls.py
secureauth/registration/views.py
secureauth/sms_backends/__init__.py
secureauth/sms_backends/nexmo_sms.py
secureauth/sms_backends/smsaero_sms.py
secureauth/sms_backends/twilio_sms.py
secureauth/south_migrations/0001_initial.py
secureauth/south_migrations/0002_auto__add_userauthlogging__add_userauthattempt.py
secureauth/south_migrations/0003_auto__chg_field_userauthphone_phone.py
secureauth/south_migrations/0004_auto__chg_field_userauthattempt_ip__chg_field_userauthphone_phone.py
secureauth/south_migrations/0005_auto__add_index_userauthactivity_ip.py
secureauth/south_migrations/0006_auto__add_field_userauthactivity_confirm_method.py
secureauth/south_migrations/0007_auto__add_userauthiprange__add_unique_userauthiprange_user_start_ip_en.py
secureauth/south_migrations/0008_auto__del_field_userauthiprange_start_ip__del_field_userauthiprange_en.py
secureauth/south_migrations/0009_auto__del_field_userauthiprange_ip_range__add_field_userauthiprange_ip.py
secureauth/south_migrations/0010_auto__del_field_userauthiprange_user__add_field_userauthiprange_ip__de.py
secureauth/south_migrations/0011_auto__add_field_userauthactivity_notified.py
secureauth/south_migrations/0012_auto__del_index_userauthattempt_ip__add_unique_userauthattempt_ip.py
secureauth/south_migrations/__init__.py
secureauth/south_migrations.old/0001_initial.py
