Metadata-Version: 2.0
Name: django-secure-auth
Version: 1.3.3.2
Summary: Secure authentication by TOTP, SMS, Codes & Question
Home-page: https://github.com/gotlium/django-secure-auth
Author: GoTLiuM InSPiRiT
Author-email: gotlium@gmail.com
License: GPL v3
Keywords: django secure auth protection totp sms codes question
Platform: UNKNOWN
Classifier: Development Status :: 5 - Production/Stable
Classifier: Environment :: Web Environment
Classifier: Framework :: Django
Classifier: Intended Audience :: Developers
Classifier: License :: OSI Approved :: GNU General Public License v3 (GPLv3)
Classifier: Operating System :: OS Independent
Classifier: Programming Language :: Python
Classifier: Programming Language :: Python :: 2.7
Requires-Dist: django-filter (>=0.7)
Requires-Dist: django-ipware (>=0.0.8)
Requires-Dist: django-phonenumber-field (>=0.5)
Requires-Dist: django-simple-captcha (>=0.4.2)
Requires-Dist: django-tables2 (>=0.14.0)
Requires-Dist: httpagentparser (>=1.5.0)
Requires-Dist: ipaddress (>=1.0.6)
Requires-Dist: phonenumbers (>=6.1.0)
Requires-Dist: pyotp (>=1.3.1)
Requires-Dist: slowaes (==0.1a1)
